[{"timestamp":1599446078227,"files":[{"filename":"ssr-bundle.0a074.css","previous":7697,"size":0,"diff":-7697},{"filename":"ssr-bundle.js","previous":21841,"size":0,"diff":-21841},{"filename":"bundle.1d63e.css","previous":0,"size":5025,"diff":5025},{"filename":"bundle.*****.esm.js","previous":0,"size":22441,"diff":22441},{"filename":"polyfills.*****.esm.js","previous":0,"size":2012,"diff":2012},{"filename":"2.chunk.19e22.css","previous":0,"size":2395,"diff":2395},{"filename":"2.chunk.*****.esm.js","previous":0,"size":1418,"diff":1418},{"filename":"3.chunk.d2c2a.css","previous":0,"size":1413,"diff":1413},{"filename":"3.chunk.*****.esm.js","previous":0,"size":1193,"diff":1193},{"filename":"4.chunk.674bc.css","previous":0,"size":1721,"diff":1721},{"filename":"4.chunk.*****.esm.js","previous":0,"size":603,"diff":603},{"filename":"sw-esm.js","previous":0,"size":8473,"diff":8473},{"filename":"sw.js","previous":0,"size":8470,"diff":8470},{"filename":"bundle.ee2e8.js","previous":0,"size":23446,"diff":23446},{"filename":"polyfills.c4c4d.js","previous":0,"size":2009,"diff":2009},{"filename":"2.chunk.a6911.js","previous":0,"size":1469,"diff":1469},{"filename":"3.chunk.5b679.js","previous":0,"size":1246,"diff":1246},{"filename":"4.chunk.92b16.js","previous":0,"size":722,"diff":722}]},{"timestamp":1599445983106,"files":[{"filename":"bundle.4f5fb.css","previous":5025,"size":0,"diff":-5025},{"filename":"bundle.*****.esm.js","previous":22424,"size":0,"diff":-22424},{"filename":"polyfills.*****.esm.js","previous":2015,"size":0,"diff":-2015},{"filename":"2.chunk.19e22.css","previous":2395,"size":0,"diff":-2395},{"filename":"2.chunk.*****.esm.js","previous":1418,"size":0,"diff":-1418},{"filename":"3.chunk.d2c2a.css","previous":1413,"size":0,"diff":-1413},{"filename":"3.chunk.*****.esm.js","previous":1193,"size":0,"diff":-1193},{"filename":"4.chunk.674bc.css","previous":1721,"size":0,"diff":-1721},{"filename":"4.chunk.*****.esm.js","previous":603,"size":0,"diff":-603},{"filename":"sw-esm.js","previous":8473,"size":0,"diff":-8473},{"filename":"sw.js","previous":8470,"size":0,"diff":-8470},{"filename":"bundle.b5dea.js","previous":23435,"size":0,"diff":-23435},{"filename":"polyfills.694cb.js","previous":2013,"size":0,"diff":-2013},{"filename":"2.chunk.a6911.js","previous":1469,"size":0,"diff":-1469},{"filename":"3.chunk.5b679.js","previous":1246,"size":0,"diff":-1246},{"filename":"4.chunk.92b16.js","previous":722,"size":0,"diff":-722},{"filename":"ssr-bundle.0a074.css","previous":0,"size":7697,"diff":7697},{"filename":"ssr-bundle.js","previous":0,"size":21841,"diff":21841}]},{"timestamp":1599445601242,"files":[{"filename":"ssr-bundle.0a074.css","previous":7697,"size":0,"diff":-7697},{"filename":"ssr-bundle.js","previous":21841,"size":0,"diff":-21841},{"filename":"bundle.4f5fb.css","previous":0,"size":5025,"diff":5025},{"filename":"bundle.*****.esm.js","previous":0,"size":22424,"diff":22424},{"filename":"polyfills.*****.esm.js","previous":0,"size":2015,"diff":2015},{"filename":"2.chunk.19e22.css","previous":0,"size":2395,"diff":2395},{"filename":"2.chunk.*****.esm.js","previous":0,"size":1418,"diff":1418},{"filename":"3.chunk.d2c2a.css","previous":0,"size":1413,"diff":1413},{"filename":"3.chunk.*****.esm.js","previous":0,"size":1193,"diff":1193},{"filename":"4.chunk.674bc.css","previous":0,"size":1721,"diff":1721},{"filename":"4.chunk.*****.esm.js","previous":0,"size":603,"diff":603},{"filename":"sw-esm.js","previous":0,"size":8473,"diff":8473},{"filename":"sw.js","previous":0,"size":8470,"diff":8470},{"filename":"bundle.b5dea.js","previous":0,"size":23435,"diff":23435},{"filename":"polyfills.694cb.js","previous":0,"size":2013,"diff":2013},{"filename":"2.chunk.a6911.js","previous":0,"size":1469,"diff":1469},{"filename":"3.chunk.5b679.js","previous":0,"size":1246,"diff":1246},{"filename":"4.chunk.92b16.js","previous":0,"size":722,"diff":722}]},{"timestamp":1599445528583,"files":[{"filename":"ssr-bundle.0a074.css","previous":0,"size":7697,"diff":7697},{"filename":"ssr-bundle.js","previous":0,"size":21841,"diff":21841}]}]
